{
  "Bounds": "0,0,451,198",
  "Dock": "None",
  "Padding": "0,0,0,0",
  "AlignmentEdgeDistances": "0,0,0,0",
  "AlignmentTransform": "0,0",
  "Margin": "0,0,0,0",
  "RenderColor": "255,255,255,255",
  "Alignments": "Center",
  "DrawBackground": true,
  "MinimumSize": "100,40",
  "MaximumSize": "0,0",
  "Disabled": false,
  "Hidden": false,
  "RestrictToParent": false,
  "MouseInputEnabled": true,
  "HideToolTip": false,
  "ToolTipBackground": null,
  "ToolTipFont": null,
  "TooltipTextColor": null,
  "ClampMovement": true,
  "DrawShadow": true,
  "ActiveImage": null,
  "InactiveImage": null,
  "ActiveColor": "255,255,255,255",
  "InactiveColor": "255,191,191,191",
  "IsClosable": false,
  "InnerPanel": {
    "Bounds": "0,28,100,12",
    "Dock": "Fill",
    "Padding": "8,8,8,8",
    "AlignmentEdgeDistances": "0,0,0,0",
    "AlignmentTransform": "0,0",
    "Margin": "0,0,0,0",
    "RenderColor": "255,255,255,255",
    "Alignments": "",
    "DrawBackground": true,
    "MinimumSize": "100,12",
    "MaximumSize": "0,0",
    "Disabled": false,
    "Hidden": false,
    "RestrictToParent": false,
    "MouseInputEnabled": true,
    "HideToolTip": false,
    "ToolTipBackground": null,
    "ToolTipFont": null,
    "TooltipTextColor": null,
    "Children": {
      "_openSettingsButton": {
        "Bounds": "0,0,87,154",
        "Dock": "Left",
        "Padding": "0,24,0,0",
        "AlignmentEdgeDistances": "0,0,0,0",
        "AlignmentTransform": "0,0",
        "Margin": "0,0,0,0",
        "RenderColor": "255,255,255,255",
        "Alignments": "",
        "DrawBackground": true,
        "MinimumSize": "0,0",
        "MaximumSize": "0,0",
        "Disabled": false,
        "Hidden": false,
        "RestrictToParent": false,
        "MouseInputEnabled": true,
        "HideToolTip": false,
        "ToolTipBackground": null,
        "ToolTipFont": null,
        "TooltipTextColor": null,
        "TextColor": null,
        "HoveredTextColor": null,
        "ClickedTextColor": null,
        "DisabledTextColor": null,
        "TextAlign": "Center",
        "AutoSizeToContents": false,
        "FontName": "sourcesansproblack",
        "FontSize": 12,
        "TextScale": 1.0,
        "NormalImage": "EscapeMenuWindow_openSettingsButton_Normal.png",
        "HoveredImage": "EscapeMenuWindow_openSettingsButton_Hovered.png",
        "ClickedImage": "EscapeMenuWindow_openSettingsButton_Active.png",
        "DisabledImage": "EscapeMenuWindow_openSettingsButton_Disabled.png",
        "_stateSoundNames": {
          "Hover": "octave-tap-resonant.wav",
          "MouseDown": "octave-tap-warm.wav",
          "MouseUp": "octave-tap-warm.wav"
        },
        "CenterImage": false
      },
      "_returnToCharacterSelectionButton": {
        "Bounds": "0,0,87,154",
        "Dock": "Left",
        "Padding": "0,24,0,0",
        "AlignmentEdgeDistances": "0,0,0,0",
        "AlignmentTransform": "0,0",
        "Margin": "0,0,0,0",
        "RenderColor": "255,255,255,255",
        "Alignments": "",
        "DrawBackground": true,
        "MinimumSize": "0,0",
        "MaximumSize": "0,0",
        "Disabled": false,
        "Hidden": false,
        "RestrictToParent": false,
        "MouseInputEnabled": true,
        "HideToolTip": false,
        "ToolTipBackground": null,
        "ToolTipFont": null,
        "TooltipTextColor": null,
        "TextColor": null,
        "HoveredTextColor": null,
        "ClickedTextColor": null,
        "DisabledTextColor": null,
        "TextAlign": "Center",
        "AutoSizeToContents": false,
        "FontName": "sourcesansproblack",
        "FontSize": 12,
        "TextScale": 1.0,
        "NormalImage": "EscapeMenuWindow_returnToCharacterSelectionButton_Normal.png",
        "HoveredImage": "EscapeMenuWindow_returnToCharacterSelectionButton_Hovered.png",
        "ClickedImage": "EscapeMenuWindow_returnToCharacterSelectionButton_Active.png",
        "DisabledImage": "EscapeMenuWindow_returnToCharacterSelectionButton_Disabled.png",
        "_stateSoundNames": {
          "Hover": "octave-tap-resonant.wav",
          "MouseDown": "octave-tap-warm.wav",
          "MouseUp": "octave-tap-warm.wav"
        },
        "CenterImage": false
      },
      "_logoutButton": {
        "Bounds": "0,0,87,154",
        "Dock": "Left",
        "Padding": "0,24,0,0",
        "AlignmentEdgeDistances": "0,0,0,0",
        "AlignmentTransform": "0,0",
        "Margin": "0,0,0,0",
        "RenderColor": "255,255,255,255",
        "Alignments": "",
        "DrawBackground": true,
        "MinimumSize": "0,0",
        "MaximumSize": "0,0",
        "Disabled": false,
        "Hidden": false,
        "RestrictToParent": false,
        "MouseInputEnabled": true,
        "HideToolTip": false,
        "ToolTipBackground": null,
        "ToolTipFont": null,
        "TooltipTextColor": null,
        "TextColor": null,
        "HoveredTextColor": null,
        "ClickedTextColor": null,
        "DisabledTextColor": null,
        "TextAlign": "Center",
        "AutoSizeToContents": false,
        "FontName": "sourcesansproblack",
        "FontSize": 12,
        "TextScale": 1.0,
        "NormalImage": "EscapeMenuWindow_logoutButton_Normal.png",
        "HoveredImage": "EscapeMenuWindow_logoutButton_Hovered.png",
        "ClickedImage": "EscapeMenuWindow_logoutButton_Active.png",
        "DisabledImage": "EscapeMenuWindow_logoutButton_Disabled.png",
        "_stateSoundNames": {
          "Hover": "octave-tap-resonant.wav",
          "MouseDown": "octave-tap-warm.wav",
          "MouseUp": "octave-tap-warm.wav"
        },
        "CenterImage": false
      },
      "_exitToDesktopButton": {
        "Bounds": "0,0,87,154",
        "Dock": "Left",
        "Padding": "0,24,0,0",
        "AlignmentEdgeDistances": "0,0,0,0",
        "AlignmentTransform": "0,0",
        "Margin": "0,0,0,0",
        "RenderColor": "255,255,255,255",
        "Alignments": "",
        "DrawBackground": true,
        "MinimumSize": "0,0",
        "MaximumSize": "0,0",
        "Disabled": false,
        "Hidden": false,
        "RestrictToParent": false,
        "MouseInputEnabled": true,
        "HideToolTip": false,
        "ToolTipBackground": null,
        "ToolTipFont": null,
        "TooltipTextColor": null,
        "TextColor": null,
        "HoveredTextColor": null,
        "ClickedTextColor": null,
        "DisabledTextColor": null,
        "TextAlign": "Center",
        "AutoSizeToContents": false,
        "FontName": "sourcesansproblack",
        "FontSize": 12,
        "TextScale": 1.0,
        "NormalImage": "EscapeMenuWindow_exitToDesktopButton_Normal.png",
        "HoveredImage": "EscapeMenuWindow_exitToDesktopButton_Hovered.png",
        "ClickedImage": "EscapeMenuWindow_exitToDesktopButton_Active.png",
        "DisabledImage": "EscapeMenuWindow_exitToDesktopButton_Disabled.png",
        "_stateSoundNames": {
          "Hover": "octave-tap-resonant.wav",
          "MouseDown": "octave-tap-warm.wav",
          "MouseUp": "octave-tap-warm.wav"
        },
        "CenterImage": false
      },
      "_returnToGameButton": {
        "Bounds": "0,0,87,154",
        "Dock": "Left",
        "Padding": "0,24,0,0",
        "AlignmentEdgeDistances": "0,0,0,0",
        "AlignmentTransform": "0,0",
        "Margin": "0,0,0,0",
        "RenderColor": "255,255,255,255",
        "Alignments": "",
        "DrawBackground": true,
        "MinimumSize": "0,0",
        "MaximumSize": "0,0",
        "Disabled": false,
        "Hidden": false,
        "RestrictToParent": false,
        "MouseInputEnabled": true,
        "HideToolTip": false,
        "ToolTipBackground": null,
        "ToolTipFont": null,
        "TooltipTextColor": null,
        "TextColor": null,
        "HoveredTextColor": null,
        "ClickedTextColor": null,
        "DisabledTextColor": null,
        "TextAlign": "Center",
        "AutoSizeToContents": false,
        "FontName": "sourcesansproblack",
        "FontSize": 12,
        "TextScale": 1.0,
        "NormalImage": "EscapeMenuWindow_returnToGameButton_Normal.png",
        "HoveredImage": "EscapeMenuWindow_returnToGameButton_Hovered.png",
        "ClickedImage": "EscapeMenuWindow_returnToGameButton_Active.png",
        "DisabledImage": "EscapeMenuWindow_returnToGameButton_Disabled.png",
        "_stateSoundNames": {
          "Hover": "octave-tap-resonant.wav",
          "MouseDown": "octave-tap-warm.wav",
          "MouseUp": "octave-tap-warm.wav"
        },
        "CenterImage": false
      }
    }
  },
  "Children": {
    "Titlebar": {
      "Bounds": "0,0,100,28",
      "Dock": "Top",
      "Padding": "4,0,0,0",
      "AlignmentEdgeDistances": "0,0,0,0",
      "AlignmentTransform": "0,0",
      "Margin": "0,0,0,0",
      "RenderColor": "255,255,255,255",
      "Alignments": "",
      "DrawBackground": true,
      "MinimumSize": "0,0",
      "MaximumSize": "0,0",
      "Disabled": false,
      "Hidden": false,
      "RestrictToParent": false,
      "MouseInputEnabled": false,
      "HideToolTip": false,
      "ToolTipBackground": null,
      "ToolTipFont": null,
      "TooltipTextColor": null,
      "NormalImage": null,
      "HoveredImage": null,
      "ClickedImage": null,
      "DisabledImage": null,
      "_stateSoundNames": {},
      "Children": {
        "_icon": {
          "Bounds": "0,4,24,24",
          "Dock": "Left",
          "Padding": "0,0,0,0",
          "AlignmentEdgeDistances": "0,0,0,0",
          "AlignmentTransform": "0,0",
          "Margin": "0,4,0,4",
          "RenderColor": "255,255,255,255",
          "Alignments": "",
          "DrawBackground": true,
          "MinimumSize": "0,0",
          "MaximumSize": "24,24",
          "Disabled": false,
          "Hidden": true,
          "RestrictToParent": false,
          "MouseInputEnabled": true,
          "HideToolTip": false,
          "ToolTipBackground": null,
          "ToolTipFont": null,
          "TooltipTextColor": null,
          "Texture": null,
          "TextureNinePatchMargin": null,
          "HoverSound": null,
          "LeftMouseClickSound": null,
          "RightMouseClickSound": null
        },
        "_label": {
          "Bounds": "4,0,96,28",
          "Dock": "CenterV, Fill",
          "Padding": "4,4,4,4",
          "AlignmentEdgeDistances": "0,0,0,0",
          "AlignmentTransform": "0,0",
          "Margin": "0,0,0,0",
          "RenderColor": "255,255,255,255",
          "Alignments": "",
          "DrawBackground": true,
          "MinimumSize": "0,0",
          "MaximumSize": "0,0",
          "Disabled": false,
          "Hidden": false,
          "RestrictToParent": false,
          "MouseInputEnabled": false,
          "HideToolTip": false,
          "ToolTipBackground": null,
          "ToolTipFont": null,
          "TooltipTextColor": null,
          "BackgroundTemplate": null,
          "TextColor": null,
          "HoveredTextColor": null,
          "ClickedTextColor": null,
          "DisabledTextColor": null,
          "TextAlign": "Left, Bottom",
          "AutoSizeToContents": false,
          "FontName": "sourcesansproblack",
          "FontSize": 14,
          "TextScale": 1.0
        },
        "CloseButton": {
          "Bounds": "0,0,28,28",
          "Dock": "Right",
          "Padding": "3,3,3,3",
          "AlignmentEdgeDistances": "0,0,0,0",
          "AlignmentTransform": "0,0",
          "Margin": "0,0,0,0",
          "RenderColor": "255,255,255,255",
          "Alignments": "",
          "DrawBackground": true,
          "MinimumSize": "0,0",
          "MaximumSize": "0,0",
          "Disabled": false,
          "Hidden": true,
          "RestrictToParent": false,
          "MouseInputEnabled": true,
          "HideToolTip": false,
          "ToolTipBackground": null,
          "ToolTipFont": null,
          "TooltipTextColor": null,
          "TextColor": null,
          "HoveredTextColor": null,
          "ClickedTextColor": null,
          "DisabledTextColor": null,
          "TextAlign": "Center",
          "AutoSizeToContents": false,
          "FontName": null,
          "FontSize": null,
          "TextScale": 1.0,
          "NormalImage": null,
          "HoveredImage": null,
          "ClickedImage": null,
          "DisabledImage": null,
          "_stateSoundNames": {
            "Hover": "octave-tap-resonant.wav",
            "MouseDown": "octave-tap-warm.wav",
            "MouseUp": "octave-tap-warm.wav"
          },
          "CenterImage": false
        }
      }
    }
  }
}